[
  {
    "id": "wi-1784741672786-ok52k",
    "name": "Stellar Engineering Concepts",
    "stage": "leading",
    "etype": "re",
    "type": "Civilisation-Scale Engineering",
    "what": "Stellar engineering involves the manipulation of stars to enhance their energy output or alter their properties, potentially providing new sources of power for advanced civilizations.",
    "source": "Breakthrough Starshot · Harvard University · NASA",
    "link": "https://www.breakthroughinitiatives.org/",
    "pubDate": "Wed, 22 Jul 2026 17:34:32 GMT",
    "photo": "/images/generated/future-tech-stellar-engineering-concepts-1784342499965.jpg"
  },
  {
    "id": "wi-1784740228702-dk8ge",
    "name": "Stellar Lifting Operations",
    "stage": "leading",
    "etype": "nu",
    "type": "Civilisation-Scale Engineering",
    "what": "Advanced techniques for extracting resources from asteroids and comets to support interstellar civilization needs.",
    "source": "SpaceX, Blue Origin",
    "link": "https://www.spacex.com/technology/stellar-lifting",
    "pubDate": "Wed, 22 Jul 2026 17:10:28 GMT",
    "photo": "/images/generated/curtech-stellar-lifting-1784337189540.jpg"
  },
  {
    "id": "wi-1784740228600-hm66r",
    "name": "Dyson Spheres and Orbital Rings",
    "stage": "leading",
    "etype": "fo",
    "type": "Civilisation-Scale Engineering",
    "what": "Exploring the feasibility of constructing Dyson spheres and orbital rings for energy capture and space habitation.",
    "source": "NASA, MIT",
    "link": "https://www.nasa.gov/feature/dyson-spheres-and-orbital-rings",
    "pubDate": "Wed, 22 Jul 2026 17:10:28 GMT",
    "photo": "/images/generated/bi-orbital-rings-1783340826029.jpg"
  },
  {
    "id": "wi-1784736995658-89b44",
    "name": "Civilisation-Scale Engineering",
    "stage": "leading",
    "etype": "st",
    "type": "Civilisation-Scale Engineering",
    "what": "Dyson spheres, orbital rings, stellar lifting, and galactic engineering projects.",
    "source": "https://www.seti.org/extraterrestrial-engineering-structures",
    "link": "https://en.wikipedia.org/wiki/Dyson_sphere",
    "pubDate": "Wed, 22 Jul 2026 16:16:35 GMT",
    "photo": "/images/generated/bi-civilisation-scale-engineering-1783220944944.jpg"
  },
  {
    "id": "wi-1784708745462-rzpvw",
    "name": "Dyson Spheres Overview",
    "stage": "leading",
    "etype": "fu",
    "type": "Civilisation-Scale Engineering",
    "what": "Overview of Dyson spheres, including their design, construction, and potential applications.",
    "source": "Wikipedia",
    "link": "https://en.wikipedia.org/wiki/Dyson_sphere",
    "pubDate": "Wed, 22 Jul 2026 08:25:45 GMT",
    "photo": "/images/generated/future-tech-dyson-spheres-as-habitable-structures-1784738613001.jpg"
  }
]